[1,["19fd13691@6c48a"],["_textureSource"],["cc.SpriteFrame","cc.SpriteAtlas"],0,[[[{"name":"eft_exp_04","rect":{"x":780,"y":1166,"width":94,"height":94},"offset":{"x":0,"y":0},"originalSize":{"width":100,"height":100},"rotated":false,"capInsets":[0,0,0,0],"packable":true,"pixelsToUnit":100,"pivot":{"x":0.5,"y":0.5},"meshType":0}],[0],0,[0],[0],[0]],[[{"name":"W_Light01","rect":{"x":1671,"y":1102,"width":104,"height":110},"offset":{"x":0.5,"y":-1},"originalSize":{"width":109,"height":114},"rotated":false,"capInsets":[0,0,0,0],"packable":true,"pixelsToUnit":100,"pivot":{"x":0.5,"y":0.5},"meshType":0}],[0],0,[0],[0],[0]],[[{"name":"board_button_on","rect":{"x":728,"y":1216,"width":112,"height":46},"offset":{"x":0,"y":0},"originalSize":{"width":112,"height":46},"rotated":true,"capInsets":[0,0,0,0],"packable":true,"pixelsToUnit":100,"pivot":{"x":0.5,"y":0.5},"meshType":0}],[0],0,[0],[0],[0]],[[{"name":"SmallSpots_02","rect":{"x":1129,"y":1308,"width":128,"height":128},"offset":{"x":0,"y":0},"originalSize":{"width":128,"height":128},"rotated":false,"capInsets":[0,0,0,0],"packable":true,"pixelsToUnit":100,"pivot":{"x":0.5,"y":0.5},"meshType":0}],[0],0,[0],[0],[0]],[[{"name":"Crown","rect":{"x":543,"y":966,"width":231,"height":152},"offset":{"x":0,"y":-0.5},"originalSize":{"width":233,"height":153},"rotated":false,"capInsets":[0,0,0,0],"packable":true,"pixelsToUnit":100,"pivot":{"x":0.5,"y":0.5},"meshType":0}],[0],0,[0],[0],[0]],[[{"name":"FG_ever_c02","rect":{"x":780,"y":1266,"width":34,"height":133},"offset":{"x":0,"y":0},"originalSize":{"width":36,"height":135},"rotated":true,"capInsets":[0,0,0,0],"packable":true,"pixelsToUnit":100,"pivot":{"x":0.5,"y":0.5},"meshType":0}],[0],0,[0],[0],[0]],[[{"name":"FX_Seq_04","rect":{"x":543,"y":666,"width":100,"height":94},"offset":{"x":0,"y":0},"originalSize":{"width":100,"height":94},"rotated":false,"capInsets":[0,0,0,0],"packable":true,"pixelsToUnit":100,"pivot":{"x":0.5,"y":0.5},"meshType":0}],[0],0,[0],[0],[0]],[[{"name":"MulBoard_01","rect":{"x":919,"y":1445,"width":204,"height":68},"offset":{"x":0,"y":0},"originalSize":{"width":204,"height":68},"rotated":true,"capInsets":[0,0,0,0],"packable":true,"pixelsToUnit":100,"pivot":{"x":0.5,"y":0.5},"meshType":0}],[0],0,[0],[0],[0]],[[{"name":"FX_Light_02","rect":{"x":1263,"y":1308,"width":128,"height":128},"offset":{"x":0,"y":0},"originalSize":{"width":128,"height":128},"rotated":false,"capInsets":[0,0,0,0],"packable":true,"pixelsToUnit":100,"pivot":{"x":0.5,"y":0.5},"meshType":0}],[0],0,[0],[0],[0]],[[{"name":"Star_12","rect":{"x":880,"y":1216,"width":50,"height":44},"offset":{"x":0,"y":0},"originalSize":{"width":50,"height":44},"rotated":false,"capInsets":[0,0,0,0],"packable":true,"pixelsToUnit":100,"pivot":{"x":0.5,"y":0.5},"meshType":0}],[0],0,[0],[0],[0]],[[{"name":"win_ways_bg","rect":{"x":649,"y":591,"width":638,"height":60},"offset":{"x":0,"y":0},"originalSize":{"width":640,"height":60},"rotated":false,"capInsets":[149,0,149,0],"packable":true,"pixelsToUnit":100,"pivot":{"x":0.5,"y":0.5},"meshType":0}],[0],0,[0],[0],[0]],[[{"name":"FG_MegaWin_mega","rect":{"x":1295,"y":3,"width":457,"height":160},"offset":{"x":5.5,"y":61},"originalSize":{"width":580,"height":326},"rotated":false,"capInsets":[0,0,0,0],"packable":true,"pixelsToUnit":100,"pivot":{"x":0.5,"y":0.5},"meshType":0}],[0],0,[0],[0],[0]],[[{"name":"FX_Seq_02","rect":{"x":543,"y":766,"width":100,"height":94},"offset":{"x":0,"y":0},"originalSize":{"width":100,"height":94},"rotated":false,"capInsets":[0,0,0,0],"packable":true,"pixelsToUnit":100,"pivot":{"x":0.5,"y":0.5},"meshType":0}],[0],0,[0],[0],[0]],[[{"name":"deal_NW_nef_05","rect":{"x":1143,"y":787,"width":129,"height":143},"offset":{"x":0,"y":0},"originalSize":{"width":131,"height":145},"rotated":true,"capInsets":[0,0,0,0],"packable":true,"pixelsToUnit":100,"pivot":{"x":0.5,"y":0.5},"meshType":0}],[0],0,[0],[0],[0]],[[{"name":"Light_02","rect":{"x":1493,"y":1209,"width":128,"height":128},"offset":{"x":0,"y":0},"originalSize":{"width":128,"height":128},"rotated":false,"capInsets":[0,0,0,0],"packable":true,"pixelsToUnit":100,"pivot":{"x":0.5,"y":0.5},"meshType":0}],[0],0,[0],[0],[0]],[[{"name":"Explosion_006","rect":{"x":494,"y":1659,"width":112,"height":113},"offset":{"x":-4,"y":-0.5},"originalSize":{"width":120,"height":120},"rotated":false,"capInsets":[0,0,0,0],"packable":true,"pixelsToUnit":100,"pivot":{"x":0.5,"y":0.5},"meshType":0}],[0],0,[0],[0],[0]],[[{"name":"Explosion_004","rect":{"x":664,"y":1657,"width":110,"height":110},"offset":{"x":-3,"y":0},"originalSize":{"width":120,"height":120},"rotated":false,"capInsets":[0,0,0,0],"packable":true,"pixelsToUnit":100,"pivot":{"x":0.5,"y":0.5},"meshType":0}],[0],0,[0],[0],[0]],[[{"name":"GoldRing_W","rect":{"x":880,"y":954,"width":256,"height":256},"offset":{"x":0,"y":0},"originalSize":{"width":256,"height":256},"rotated":false,"capInsets":[0,0,0,0],"packable":true,"pixelsToUnit":100,"pivot":{"x":0.5,"y":0.5},"meshType":0}],[0],0,[0],[0],[0]],[[{"name":"eft_bol_01","rect":{"x":440,"y":1046,"width":40,"height":40},"offset":{"x":0,"y":0},"originalSize":{"width":40,"height":40},"rotated":false,"capInsets":[0,0,0,0],"packable":true,"pixelsToUnit":100,"pivot":{"x":0.5,"y":0.5},"meshType":0}],[0],0,[0],[0],[0]],[[{"name":"4win","rect":{"x":1397,"y":1304,"width":100,"height":87},"offset":{"x":0,"y":0.5},"originalSize":{"width":100,"height":100},"rotated":true,"capInsets":[0,0,0,0],"packable":true,"pixelsToUnit":100,"pivot":{"x":0.5,"y":0.5},"meshType":0}],[0],0,[0],[0],[0]],[[{"name":"Explosion_007","rect":{"x":494,"y":1216,"width":112,"height":111},"offset":{"x":-4,"y":-0.5},"originalSize":{"width":120,"height":120},"rotated":true,"capInsets":[0,0,0,0],"packable":true,"pixelsToUnit":100,"pivot":{"x":0.5,"y":0.5},"meshType":0}],[0],0,[0],[0],[0]],[[{"name":"Num_2","rect":{"x":1672,"y":838,"width":35,"height":51},"offset":{"x":0,"y":-1},"originalSize":{"width":37,"height":55},"rotated":false,"capInsets":[0,0,0,0],"packable":true,"pixelsToUnit":100,"pivot":{"x":0.5,"y":0.5},"meshType":0}],[0],0,[0],[0],[0]],[[{"name":"Explosion_012","rect":{"x":1386,"y":1209,"width":89,"height":101},"offset":{"x":-4.5,"y":-1.5},"originalSize":{"width":120,"height":120},"rotated":true,"capInsets":[0,0,0,0],"packable":true,"pixelsToUnit":100,"pivot":{"x":0.5,"y":0.5},"meshType":0}],[0],0,[0],[0],[0]],[[{"name":"Poker","rect":{"x":1143,"y":922,"width":135,"height":178},"offset":{"x":0,"y":0},"originalSize":{"width":187,"height":210},"rotated":false,"capInsets":[0,0,0,0],"packable":true,"pixelsToUnit":100,"pivot":{"x":0.5,"y":0.5},"meshType":0}],[0],0,[0],[0],[0]],[[{"name":"PokSyb_sca_s7","rect":{"x":3,"y":1106,"width":97,"height":124},"offset":{"x":0,"y":0},"originalSize":{"width":99,"height":126},"rotated":true,"capInsets":[0,0,0,0],"packable":true,"pixelsToUnit":100,"pivot":{"x":0.5,"y":0.5},"meshType":0}],[0],0,[0],[0],[0]],[[{"name":"FX_Seq_01","rect":{"x":543,"y":866,"width":100,"height":94},"offset":{"x":0,"y":0},"originalSize":{"width":100,"height":94},"rotated":false,"capInsets":[0,0,0,0],"packable":true,"pixelsToUnit":100,"pivot":{"x":0.5,"y":0.5},"meshType":0}],[0],0,[0],[0],[0]],[[{"name":"Explosion_008","rect":{"x":3,"y":992,"width":110,"height":108},"offset":{"x":-4,"y":-1},"originalSize":{"width":120,"height":120},"rotated":false,"capInsets":[0,0,0,0],"packable":true,"pixelsToUnit":100,"pivot":{"x":0.5,"y":0.5},"meshType":0}],[0],0,[0],[0],[0]],[[{"name":"FX_Seq_05","rect":{"x":780,"y":954,"width":100,"height":94},"offset":{"x":0,"y":0},"originalSize":{"width":100,"height":94},"rotated":true,"capInsets":[0,0,0,0],"packable":true,"pixelsToUnit":100,"pivot":{"x":0.5,"y":0.5},"meshType":0}],[0],0,[0],[0],[0]],[[{"name":"Scene","spriteFrames":["FG_result_c01","5f5tu5RWBGc4toE4x7WXQh@f9941","DD_02","5erQyAFnNDvZaR68/WWbQN@f9941","FG_MegaWin_mega","22esN8a7hNqau7zJl5bMzV@f9941","FX_Star_01","b8ZRmomiJCEZ4k/zhS4voY@f9941","deal_v2_c04","86z6/H5UtLwoqkj0AkDK/c@f9941","bracket1_1","65oo7m3KVE6azx6FLa8yzY@f9941","Light_11","d9xHg7VIRFSqI6T0S6Mcj9@f9941","Bs","6cYCQh3E1DZp9+SmHLrW27@f9941","Num_x","6b1Fs1PR1KlrUpyWa6o6xh@f9941","Gold_03b","acJQIvruxL94gEGa3BlTaG@f9941","board_frames","601Td4aapGOYJC0aQRdBF0@f9941","Bg_Black","c5Ad8ndFVED74QUsjmMpCF@f9941","Combo_bg","d1m499u9RPAL3YfV1aKkzv@f9941","Ts","a3R9NJiiNETpP0fCfMby3Y@f9941","FG_Multiplier_BG","d01FXyn3xDBomooW5geVnw@f9941","Light_12","acJL/YXwRJ5JPaYdPOlPhI@f9941","deal_NW_nef_03","5aj676hBdB6p/44KNqgeWd@f9941","FG_str_c02","e6GQnbu7dJqpYN7QZh0NHf@f9941","1f_star_6","f0mPVaWXhC4IhBeZwT9jre@f9941","win_ways_bg","206qg9ge1HB4w1TBpiqG50@f9941","deal_NW_nef_06","c9mUCVw7NPJbi5xCwc5SZ+@f9941","deal_NW_c01","d8EKi87vhPUK4xRuV6O98D@f9941","LRs","a3BUtce7xKUJH3T7SL1vAJ@f9941","PokSyb_sca_s4","572gM/YQFHhrupYRkfrIjF@f9941","BG_Top","eatoCMG4xDTp3ukwYHrP1p@f9941","FX_Seq_04","18Z5o9rPVGoKbWq49uZogZ@f9941","FX_Seq_02","222YbWwexHeLhFFrrhM/pN@f9941","FG_SuperWin_super","406sIN5/1CMKEquRAxwkn8@f9941","FX_Seq_01","397IMXc79L5oyMBrq1gaCO@f9941","deal_NW_nef_05","22+iP3RCpEaKxRGRquu2O2@f9941","FG_BigWin_win","d5v5w8UClHIp2gM09QZPDO@f9941","Num_2","3586KlMEBHX4DMdps3u4Cx@f9941","Explosion_013","64jVe1fKlAvo1pPT1WEpnw@f9941","eft_ligpoint_01","6cXPMnz15NK7TtNd3Men0H@f9941","Poker","38Cdx7Z5pIQZrkD4VSUTnD@f9941","FG_SuperWin_win","48xq0aaT9JxaNBGiiM5V/q@f9941","deal_v2_c05","d2Y2EbyrRNepyX7eT1nZ/c@f9941","W_Light01","06oajDiyZODaW/uX6Y6QMR@f9941","PokSyb_sca_s5","cfKH+DWoJLGYnFf6y2PXRq@f9941","Explosion_003","9eUUnNy3dHgan2qKNsvmWo@f9941","FG_MegaWin_win","78ZAkXKP9FR4o94hOiwVsD@f9941","board_button_Tip","4at8d055pFXaGCHCZu8V49@f9941","Light_05","6ayGAdSi5MDrxThEQFcAPQ@f9941","PokSyb_sca_s7","39EObkX6xP8rCtL8HxSOes@f9941","Explosion_008","3bBvz2YDlEgqx6igx1/+3y@f9941","Explosion_002","b8FCB2/kJNVIK8ClLQf4sO@f9941","deal_v2_c03","c6eMoWXaZMdKVkg3z10GmB@f9941","Explosion_010","5aK9GSBNJBr4k4dQHjmgyF@f9941","PokSyb_sca_s3","cfo5cBRFpFBrSsHpV7DDeB@f9941","Explosion_001","9anzb0frlGOq1qciNhMFyT@f9941","Explosion_014","c0EHdS9/dEBZZHBUf9zPWw@f9941","Board","8foN2NpLlPvqtYgC2cRzkI@f9941","PokSyb_sca_s2","bdv9xhTjNPWZr58TXEXKNN@f9941","WIN_num_bg","b7s/XSQlFA4o5DON05oxZ1@f9941","PokSyb_sca_s8","aezvXFYfVFhbWD7au/CgPv@f9941","FG_BigWin_big","449g+PPz9AaoAuMzZKpjLg@f9941","Exp_Light","69aqtn2IJIFos3ZTv0Lmzc@f9941","Gold_04b","60t4WAZTZHp6GmNqk4IsL+@f9941","Explosion_006","2dtV6UaK1I/ac6vttFuyKY@f9941","FG_text_light_01","78IGhWQCpG97TOkDu4qVRv@f9941","GoldRing_W","2e90pXY+tJwJL4HBJpVzpk@f9941","Explosion_007","35x7KIEkFGtqD3TJYDfQAe@f9941","Explosion_005","3fMxzt10tDn6430rYcERz2@f9941","board_button_on","0aeVbIKK9JZJx40BTJBhZy@f9941","FX_Seq_05","3cOIJJ6L1B8agzNkam4gQt@f9941","Crown","0eeNTQjrFPIrMj3wGwGOZ7@f9941","MulBoard_Light","768gR1GxtISrZ9e6rUkxoj@f9941","board_button_q","cfKReBbadJlYm/Et4WHVJ6@f9941","FX_Seq_03","69kXzHRONHoa8UqQGUW/hF@f9941","eft_exp_04","6eMoUsCdVHa5sruNZS9vqz@f9941","Explosion_016","5b6o6M6TxKtZvtuSl7EhT+@f9941","PokSyb_sca_s6","f9a8QRM+ZLz4P52SekvfMA@f9941","bracket1_2","93V2oL3lRPS6O6gHLhNQft@f9941","deal_NW_nef_01","af63vzIGNIJYzjUwVTk6As@f9941","FG_WIN_board","77Fg3mqOBHE4GR1x0Zpy7y@f9941","Black_Matte","ddVqLVJGtJlJSGHOeYAz4k@f9941","eft_bg_01","ffsyVcr9pMvZpTlegDpiHX@f9941","FG_ever_c02","11Fep1hGFFCrWcGv83E02E@f9941","Star_12","1ctDn+SgpHLJB00cX6vYVc@f9941","eft_bol_01","beiiCOYAxLHL710AATz17Z@f9941","board_button_off","7fFMri63JOkJKQ3681B+lF@f9941","Explosion_004","2d2sRYm+RKVYrCqIGWCtna@f9941","Star_17s","aaybPR6hVFMquf+R+6Sbx1@f9941","FX_Brushing_01","c6NgrzyaBH868IVXVBuA7d@f9941","FG_ever_c04","81BIFr1E5DO6YwZ0KnFiCG@f9941","deal_NW_nef_02","81CgJx6tpOqpL2xF+4XAJp@f9941","FG_text_e1","85zqAuVLFKrLNdMsT3Nny8@f9941","Explosion_009","bd8FIS+exNbpJsg/jYRQ7c@f9941","Board_ways_bg","fcQWIRycVHpZccR8s6whoH@f9941","deal_v2_c02","aaE4IGaT1DDqB7OUPiXPUh@f9941","MulBoard_01","1bVLoFtf1PbKsG7+9TXM07@f9941","MulBoard_02","f5msruNJRFB4zs9NVEUBcf@f9941","FG_ever_c01","49BoFQQRRKrK3+hFQBqO62@f9941","PokSyb_sca_s1","c4jxpfuTFGmq8JmVpE9E8G@f9941","SmallSpots_02","0dja4kEMNHXb5lma1DH5ez@f9941","deal_v2_c01","7bqPXrONlDgpB050Q2tVwd@f9941","FX_Light_02","6cuTBwXAlD/KGTbAKoJ5Zt@f9941","Explosion_011","94KHKvP2lOVqoxAWMEpsxz@f9941","Explosion_012","36xIAv+hJF+rv6M6fUs6Tx@f9941","Light_02","edxdc3xcVGKqQPrT2pNKbj@f9941","4win","f782ZToJVJUI3hNyHYSJxR@f9941","Light_02_01","3dUHNPPkZFqL5uOKsIx+vR@f9941","FX_Light_04","d030eKvY1HfJRE8RUv+HgC@f9941","MulBoard_EX","aeHG/TcfJC45P+sjaKa+oo@f9941","board_button_EX","5ePLm57qBC1KGZgMzgTjJK@f9941","Explosion_015","c3cDpVtj9H2q91mfKrOZzT@f9941","eft_str_m03","c5uJOjEl9IKLvFBMEMsedU@f9941","eft_bol_02","dezRCumkNB9rX6tjRn4T72@f9941","Gold_02b","dftMoYQrlDHaLIXNeq4LTj@f9941","deal_NW_nef_04A","bdvYIG2XFED5a4CIoLDqMu@f9941"]}],[1],0,[],[],[]],[[{"name":"Light_02_01","rect":{"x":1203,"y":1628,"width":128,"height":128},"offset":{"x":0,"y":0},"originalSize":{"width":128,"height":128},"rotated":false,"capInsets":[0,0,0,0],"packable":true,"pixelsToUnit":100,"pivot":{"x":0.5,"y":0.5},"meshType":0}],[0],0,[0],[0],[0]],[[{"name":"Explosion_005","rect":{"x":611,"y":1216,"width":111,"height":112},"offset":{"x":-3.5,"y":0},"originalSize":{"width":120,"height":120},"rotated":false,"capInsets":[0,0,0,0],"packable":true,"pixelsToUnit":100,"pivot":{"x":0.5,"y":0.5},"meshType":0}],[0],0,[0],[0],[0]],[[{"name":"FG_SuperWin_super","rect":{"x":649,"y":787,"width":488,"height":161},"offset":{"x":6,"y":61.5},"originalSize":{"width":580,"height":326},"rotated":false,"capInsets":[0,0,0,0],"packable":true,"pixelsToUnit":100,"pivot":{"x":0.5,"y":0.5},"meshType":0}],[0],0,[0],[0],[0]],[[{"name":"FG_BigWin_big","rect":{"x":410,"y":1334,"width":319,"height":195},"offset":{"x":5.5,"y":59.5},"originalSize":{"width":580,"height":326},"rotated":true,"capInsets":[0,0,0,0],"packable":true,"pixelsToUnit":100,"pivot":{"x":0.5,"y":0.5},"meshType":0}],[0],0,[0],[0],[0]],[[{"name":"FG_SuperWin_win","rect":{"x":1284,"y":1039,"width":344,"height":164},"offset":{"x":5,"y":-57},"originalSize":{"width":580,"height":326},"rotated":false,"capInsets":[0,0,0,0],"packable":true,"pixelsToUnit":100,"pivot":{"x":0.5,"y":0.5},"meshType":0}],[0],0,[0],[0],[0]],[[{"name":"FG_ever_c01","rect":{"x":1067,"y":1445,"width":202,"height":89},"offset":{"x":0,"y":0},"originalSize":{"width":204,"height":91},"rotated":true,"capInsets":[0,0,0,0],"packable":true,"pixelsToUnit":100,"pivot":{"x":0.5,"y":0.5},"meshType":0}],[0],0,[0],[0],[0]],[[{"name":"board_button_Tip","rect":{"x":3,"y":1684,"width":226,"height":93},"offset":{"x":0,"y":0},"originalSize":{"width":226,"height":93},"rotated":false,"capInsets":[18,18,18,18],"packable":true,"pixelsToUnit":100,"pivot":{"x":0.5,"y":0.5},"meshType":0}],[0],0,[0],[0],[0]],[[{"name":"PokSyb_sca_s4","rect":{"x":1223,"y":657,"width":66,"height":124},"offset":{"x":0,"y":0},"originalSize":{"width":68,"height":126},"rotated":false,"capInsets":[0,0,0,0],"packable":true,"pixelsToUnit":100,"pivot":{"x":0.5,"y":0.5},"meshType":0}],[0],0,[0],[0],[0]],[[{"name":"Explosion_010","rect":{"x":133,"y":1106,"width":92,"height":97},"offset":{"x":-2,"y":-0.5},"originalSize":{"width":120,"height":120},"rotated":false,"capInsets":[0,0,0,0],"packable":true,"pixelsToUnit":100,"pivot":{"x":0.5,"y":0.5},"meshType":0}],[0],0,[0],[0],[0]],[[{"name":"deal_NW_nef_03","rect":{"x":1721,"y":415,"width":99,"height":52},"offset":{"x":0,"y":-0.5},"originalSize":{"width":99,"height":57},"rotated":true,"capInsets":[0,0,0,0],"packable":true,"pixelsToUnit":100,"pivot":{"x":0.5,"y":0.5},"meshType":0}],[0],0,[0],[0],[0]],[[{"name":"Explosion_016","rect":{"x":543,"y":1124,"width":84,"height":99},"offset":{"x":-3,"y":-4.5},"originalSize":{"width":120,"height":120},"rotated":true,"capInsets":[0,0,0,0],"packable":true,"pixelsToUnit":100,"pivot":{"x":0.5,"y":0.5},"meshType":0}],[0],0,[0],[0],[0]],[[{"name":"board_button_EX","rect":{"x":1290,"y":1529,"width":87,"height":66},"offset":{"x":0,"y":0},"originalSize":{"width":87,"height":66},"rotated":true,"capInsets":[0,0,0,0],"packable":true,"pixelsToUnit":100,"pivot":{"x":0.5,"y":0.5},"meshType":0}],[0],0,[0],[0],[0]],[[{"name":"DD_02","rect":{"x":649,"y":3,"width":640,"height":206},"offset":{"x":0,"y":0},"originalSize":{"width":640,"height":206},"rotated":false,"capInsets":[0,0,0,0],"packable":true,"pixelsToUnit":100,"pivot":{"x":0.5,"y":0.5},"meshType":0}],[0],0,[0],[0],[0]],[[{"name":"FG_result_c01","rect":{"x":3,"y":3,"width":640,"height":581},"offset":{"x":0,"y":0},"originalSize":{"width":642,"height":583},"rotated":false,"capInsets":[0,0,0,0],"packable":true,"pixelsToUnit":100,"pivot":{"x":0.5,"y":0.5},"meshType":0}],[0],0,[0],[0],[0]],[[{"name":"Gold_04b","rect":{"x":281,"y":1208,"width":73,"height":76},"offset":{"x":-2,"y":1.5},"originalSize":{"width":85,"height":85},"rotated":false,"capInsets":[0,0,0,0],"packable":true,"pixelsToUnit":100,"pivot":{"x":0.5,"y":0.5},"meshType":0}],[0],0,[0],[0],[0]],[[{"name":"board_frames","rect":{"x":1723,"y":287,"width":54,"height":59},"offset":{"x":-5,"y":1.5},"originalSize":{"width":64,"height":64},"rotated":false,"capInsets":[6.5,0,45.5,0],"packable":true,"pixelsToUnit":100,"pivot":{"x":0.5,"y":0.5},"meshType":0}],[0],0,[0],[0],[0]],[[{"name":"Explosion_013","rect":{"x":1672,"y":1013,"width":83,"height":105},"offset":{"x":-3.5,"y":-1.5},"originalSize":{"width":120,"height":120},"rotated":true,"capInsets":[0,0,0,0],"packable":true,"pixelsToUnit":100,"pivot":{"x":0.5,"y":0.5},"meshType":0}],[0],0,[0],[0],[0]],[[{"name":"bracket1_1","rect":{"x":1758,"y":148,"width":12,"height":40},"offset":{"x":0,"y":-0.5},"originalSize":{"width":12,"height":41},"rotated":false,"capInsets":[0,0,0,0],"packable":true,"pixelsToUnit":100,"pivot":{"x":0.5,"y":0.5},"meshType":0}],[0],0,[0],[0],[0]],[[{"name":"Exp_Light","rect":{"x":360,"y":1106,"width":218,"height":128},"offset":{"x":0,"y":0},"originalSize":{"width":218,"height":128},"rotated":true,"capInsets":[0,0,0,0],"packable":true,"pixelsToUnit":100,"pivot":{"x":0.5,"y":0.5},"meshType":0}],[0],0,[0],[0],[0]],[[{"name":"FX_Seq_03","rect":{"x":780,"y":1060,"width":100,"height":94},"offset":{"x":0,"y":0},"originalSize":{"width":100,"height":94},"rotated":true,"capInsets":[0,0,0,0],"packable":true,"pixelsToUnit":100,"pivot":{"x":0.5,"y":0.5},"meshType":0}],[0],0,[0],[0],[0]],[[{"name":"Light_05","rect":{"x":3,"y":1209,"width":117,"height":115},"offset":{"x":-2.5,"y":-0.5},"originalSize":{"width":128,"height":128},"rotated":true,"capInsets":[0,0,0,0],"packable":true,"pixelsToUnit":100,"pivot":{"x":0.5,"y":0.5},"meshType":0}],[0],0,[0],[0],[0]],[[{"name":"Num_x","rect":{"x":1723,"y":169,"width":29,"height":29},"offset":{"x":0,"y":-2},"originalSize":{"width":37,"height":55},"rotated":false,"capInsets":[0,0,0,0],"packable":true,"pixelsToUnit":100,"pivot":{"x":0.5,"y":0.5},"meshType":0}],[0],0,[0],[0],[0]],[[{"name":"eft_ligpoint_01","rect":{"x":1672,"y":895,"width":100,"height":33},"offset":{"x":0,"y":0},"originalSize":{"width":100,"height":33},"rotated":true,"capInsets":[0,0,0,0],"packable":true,"pixelsToUnit":100,"pivot":{"x":0.5,"y":0.5},"meshType":0}],[0],0,[0],[0],[0]],[[{"name":"Bs","rect":{"x":649,"y":215,"width":640,"height":182},"offset":{"x":0,"y":0},"originalSize":{"width":640,"height":182},"rotated":false,"capInsets":[0,0,0,0],"packable":true,"pixelsToUnit":100,"pivot":{"x":0.5,"y":0.5},"meshType":0}],[0],0,[0],[0],[0]],[[{"name":"FX_Light_02","rect":{"x":1627,"y":1334,"width":128,"height":128},"offset":{"x":0,"y":0},"originalSize":{"width":128,"height":128},"rotated":false,"capInsets":[0,0,0,0],"packable":true,"pixelsToUnit":100,"pivot":{"x":0.5,"y":0.5},"meshType":0}],[0],0,[0],[0],[0]],[[{"name":"eft_exp_04","rect":{"x":1624,"y":1602,"width":94,"height":94},"offset":{"x":0,"y":0},"originalSize":{"width":100,"height":100},"rotated":false,"capInsets":[0,0,0,0],"packable":true,"pixelsToUnit":100,"pivot":{"x":0.5,"y":0.5},"meshType":0}],[0],0,[0],[0],[0]],[[{"name":"MulBoard_Light","rect":{"x":494,"y":992,"width":212,"height":43},"offset":{"x":0,"y":0},"originalSize":{"width":212,"height":43},"rotated":true,"capInsets":[0,0,0,0],"packable":true,"pixelsToUnit":100,"pivot":{"x":0.5,"y":0.5},"meshType":0}],[0],0,[0],[0],[0]],[[{"name":"FG_WIN_board","rect":{"x":1142,"y":1106,"width":196,"height":134},"offset":{"x":0,"y":0},"originalSize":{"width":196,"height":134},"rotated":true,"capInsets":[0,0,0,0],"packable":true,"pixelsToUnit":100,"pivot":{"x":0.5,"y":0.5},"meshType":0}],[0],0,[0],[0],[0]],[[{"name":"FG_text_light_01","rect":{"x":611,"y":1334,"width":317,"height":263},"offset":{"x":0,"y":0},"originalSize":{"width":317,"height":263},"rotated":true,"capInsets":[0,0,0,0],"packable":true,"pixelsToUnit":100,"pivot":{"x":0.5,"y":0.5},"meshType":0}],[0],0,[0],[0],[0]],[[{"name":"FG_MegaWin_win","rect":{"x":3,"y":1334,"width":344,"height":159},"offset":{"x":6,"y":-55.5},"originalSize":{"width":580,"height":326},"rotated":true,"capInsets":[0,0,0,0],"packable":true,"pixelsToUnit":100,"pivot":{"x":0.5,"y":0.5},"meshType":0}],[0],0,[0],[0],[0]],[[{"name":"deal_v2_c01","rect":{"x":1162,"y":1442,"width":122,"height":180},"offset":{"x":0,"y":1.5},"originalSize":{"width":122,"height":183},"rotated":false,"capInsets":[0,0,0,0],"packable":true,"pixelsToUnit":100,"pivot":{"x":0.5,"y":0.5},"meshType":0}],[0],0,[0],[0],[0]],[[{"name":"board_button_off","rect":{"x":612,"y":1657,"width":112,"height":46},"offset":{"x":0,"y":0},"originalSize":{"width":112,"height":46},"rotated":true,"capInsets":[0,0,0,0],"packable":true,"pixelsToUnit":100,"pivot":{"x":0.5,"y":0.5},"meshType":0}],[0],0,[0],[0],[0]],[[{"name":"FG_ever_c04","rect":{"x":936,"y":1216,"width":40,"height":40},"offset":{"x":0,"y":0},"originalSize":{"width":42,"height":42},"rotated":false,"capInsets":[0,0,0,0],"packable":true,"pixelsToUnit":100,"pivot":{"x":0.5,"y":0.5},"meshType":0}],[0],0,[0],[0],[0]],[[{"name":"deal_NW_nef_02","rect":{"x":982,"y":1216,"width":40,"height":40},"offset":{"x":0,"y":0},"originalSize":{"width":42,"height":42},"rotated":false,"capInsets":[0,0,0,0],"packable":true,"pixelsToUnit":100,"pivot":{"x":0.5,"y":0.5},"meshType":0}],[0],0,[0],[0],[0]],[[{"name":"FG_text_e1","rect":{"x":1028,"y":1216,"width":40,"height":40},"offset":{"x":0,"y":0},"originalSize":{"width":40,"height":40},"rotated":false,"capInsets":[0,0,0,0],"packable":true,"pixelsToUnit":100,"pivot":{"x":0.5,"y":0.5},"meshType":0}],[0],0,[0],[0],[0]],[[{"name":"deal_v2_c04","rect":{"x":1758,"y":24,"width":118,"height":15},"offset":{"x":0.5,"y":0},"originalSize":{"width":121,"height":15},"rotated":true,"capInsets":[0,0,0,0],"packable":true,"pixelsToUnit":100,"pivot":{"x":0.5,"y":0.5},"meshType":0}],[0],0,[0],[0],[0]],[[{"name":"Board","rect":{"x":168,"y":1334,"width":320,"height":154},"offset":{"x":0,"y":0},"originalSize":{"width":320,"height":154},"rotated":true,"capInsets":[0,0,0,0],"packable":true,"pixelsToUnit":100,"pivot":{"x":0.5,"y":0.5},"meshType":0}],[0],0,[0],[0],[0]],[[{"name":"bracket1_2","rect":{"x":648,"y":1196,"width":12,"height":40},"offset":{"x":0,"y":-0.5},"originalSize":{"width":12,"height":41},"rotated":true,"capInsets":[0,0,0,0],"packable":true,"pixelsToUnit":100,"pivot":{"x":0.5,"y":0.5},"meshType":0}],[0],0,[0],[0],[0]],[[{"name":"Explosion_011","rect":{"x":1282,"y":1209,"width":90,"height":98},"offset":{"x":-4,"y":-2},"originalSize":{"width":120,"height":120},"rotated":true,"capInsets":[0,0,0,0],"packable":true,"pixelsToUnit":100,"pivot":{"x":0.5,"y":0.5},"meshType":0}],[0],0,[0],[0],[0]],[[{"name":"Explosion_001","rect":{"x":235,"y":992,"width":110,"height":107},"offset":{"x":-3,"y":0.5},"originalSize":{"width":120,"height":120},"rotated":false,"capInsets":[0,0,0,0],"packable":true,"pixelsToUnit":100,"pivot":{"x":0.5,"y":0.5},"meshType":0}],[0],0,[0],[0],[0]],[[{"name":"Explosion_003","rect":{"x":1668,"y":1218,"width":110,"height":109},"offset":{"x":-3,"y":0.5},"originalSize":{"width":120,"height":120},"rotated":true,"capInsets":[0,0,0,0],"packable":true,"pixelsToUnit":100,"pivot":{"x":0.5,"y":0.5},"meshType":0}],[0],0,[0],[0],[0]],[[{"name":"LRs","rect":{"x":649,"y":657,"width":124,"height":568},"offset":{"x":0,"y":0},"originalSize":{"width":124,"height":568},"rotated":true,"capInsets":[0,0,0,0],"packable":true,"pixelsToUnit":100,"pivot":{"x":0.5,"y":0.5},"meshType":0}],[0],0,[0],[0],[0]],[[{"name":"Ts","rect":{"x":649,"y":403,"width":640,"height":182},"offset":{"x":0,"y":0},"originalSize":{"width":640,"height":182},"rotated":false,"capInsets":[0,0,0,0],"packable":true,"pixelsToUnit":100,"pivot":{"x":0.5,"y":0.5},"meshType":0}],[0],0,[0],[0],[0]],[[{"name":"deal_v2_c02","rect":{"x":885,"y":1656,"width":121,"height":183},"offset":{"x":0.5,"y":0},"originalSize":{"width":122,"height":183},"rotated":true,"capInsets":[0,0,0,0],"packable":true,"pixelsToUnit":100,"pivot":{"x":0.5,"y":0.5},"meshType":0}],[0],0,[0],[0],[0]],[[{"name":"Star_17s","rect":{"x":919,"y":1266,"width":204,"height":173},"offset":{"x":0.5,"y":-3.5},"originalSize":{"width":211,"height":180},"rotated":false,"capInsets":[0,0,0,0],"packable":true,"pixelsToUnit":100,"pivot":{"x":0.5,"y":0.5},"meshType":0}],[0],0,[0],[0],[0]],[[{"name":"Light_12","rect":{"x":1721,"y":352,"width":57,"height":56},"offset":{"x":3.5,"y":-1},"originalSize":{"width":64,"height":64},"rotated":true,"capInsets":[0,0,0,0],"packable":true,"pixelsToUnit":100,"pivot":{"x":0.5,"y":0.5},"meshType":0}],[0],0,[0],[0],[0]],[[{"name":"Gold_03b","rect":{"x":1723,"y":204,"width":77,"height":54},"offset":{"x":1,"y":-2.5},"originalSize":{"width":85,"height":85},"rotated":true,"capInsets":[0,0,0,0],"packable":true,"pixelsToUnit":100,"pivot":{"x":0.5,"y":0.5},"meshType":0}],[0],0,[0],[0],[0]],[[{"name":"MulBoard_EX","rect":{"x":1290,"y":1442,"width":100,"height":81},"offset":{"x":1,"y":-0.5},"originalSize":{"width":102,"height":82},"rotated":false,"capInsets":[0,0,0,0],"packable":true,"pixelsToUnit":100,"pivot":{"x":0.5,"y":0.5},"meshType":0}],[0],0,[0],[0],[0]],[[{"name":"PokSyb_sca_s8","rect":{"x":365,"y":1660,"width":116,"height":123},"offset":{"x":-0.5,"y":-0.5},"originalSize":{"width":119,"height":126},"rotated":true,"capInsets":[0,0,0,0],"packable":true,"pixelsToUnit":100,"pivot":{"x":0.5,"y":0.5},"meshType":0}],[0],0,[0],[0],[0]],[[{"name":"deal_NW_nef_01","rect":{"x":694,"y":1196,"width":11,"height":80},"offset":{"x":0,"y":0},"originalSize":{"width":11,"height":80},"rotated":true,"capInsets":[0,0,0,0],"packable":true,"pixelsToUnit":100,"pivot":{"x":0.5,"y":0.5},"meshType":0}],[0],0,[0],[0],[0]],[[{"name":"WIN_num_bg","rect":{"x":328,"y":1334,"width":320,"height":76},"offset":{"x":0,"y":0},"originalSize":{"width":320,"height":76},"rotated":true,"capInsets":[0,0,0,0],"packable":true,"pixelsToUnit":100,"pivot":{"x":0.5,"y":0.5},"meshType":0}],[0],0,[0],[0],[0]],[[{"name":"Explosion_002","rect":{"x":119,"y":992,"width":110,"height":108},"offset":{"x":-3,"y":0},"originalSize":{"width":120,"height":120},"rotated":false,"capInsets":[0,0,0,0],"packable":true,"pixelsToUnit":100,"pivot":{"x":0.5,"y":0.5},"meshType":0}],[0],0,[0],[0],[0]],[[{"name":"FX_Star_01","rect":{"x":1758,"y":3,"width":15,"height":16},"offset":{"x":-0.5,"y":0},"originalSize":{"width":16,"height":16},"rotated":true,"capInsets":[0,0,0,0],"packable":true,"pixelsToUnit":100,"pivot":{"x":0.5,"y":0.5},"meshType":0}],[0],0,[0],[0],[0]],[[{"name":"deal_NW_nef_04A","rect":{"x":1484,"y":1611,"width":76,"height":76},"offset":{"x":0,"y":0},"originalSize":{"width":80,"height":80},"rotated":false,"capInsets":[0,0,0,0],"packable":true,"pixelsToUnit":100,"pivot":{"x":0.5,"y":0.5},"meshType":0}],[0],0,[0],[0],[0]],[[{"name":"PokSyb_sca_s2","rect":{"x":235,"y":1660,"width":116,"height":124},"offset":{"x":0,"y":0},"originalSize":{"width":118,"height":126},"rotated":true,"capInsets":[0,0,0,0],"packable":true,"pixelsToUnit":100,"pivot":{"x":0.5,"y":0.5},"meshType":0}],[0],0,[0],[0],[0]],[[{"name":"Explosion_009","rect":{"x":780,"y":1657,"width":99,"height":102},"offset":{"x":-2.5,"y":-1},"originalSize":{"width":120,"height":120},"rotated":false,"capInsets":[0,0,0,0],"packable":true,"pixelsToUnit":100,"pivot":{"x":0.5,"y":0.5},"meshType":0}],[0],0,[0],[0],[0]],[[{"name":"eft_bol_01","rect":{"x":1074,"y":1216,"width":40,"height":40},"offset":{"x":0,"y":0},"originalSize":{"width":40,"height":40},"rotated":false,"capInsets":[0,0,0,0],"packable":true,"pixelsToUnit":100,"pivot":{"x":0.5,"y":0.5},"meshType":0}],[0],0,[0],[0],[0]],[[{"name":"Explosion_014","rect":{"x":351,"y":992,"width":83,"height":107},"offset":{"x":-3.5,"y":-1.5},"originalSize":{"width":120,"height":120},"rotated":false,"capInsets":[0,0,0,0],"packable":true,"pixelsToUnit":100,"pivot":{"x":0.5,"y":0.5},"meshType":0}],[0],0,[0],[0],[0]],[[{"name":"Explosion_015","rect":{"x":1396,"y":1516,"width":82,"height":102},"offset":{"x":-4,"y":-3},"originalSize":{"width":120,"height":120},"rotated":false,"capInsets":[0,0,0,0],"packable":true,"pixelsToUnit":100,"pivot":{"x":0.5,"y":0.5},"meshType":0}],[0],0,[0],[0],[0]],[[{"name":"PokSyb_sca_s1","rect":{"x":1074,"y":1653,"width":123,"height":123},"offset":{"x":0,"y":-0.5},"originalSize":{"width":125,"height":126},"rotated":false,"capInsets":[0,0,0,0],"packable":true,"pixelsToUnit":100,"pivot":{"x":0.5,"y":0.5},"meshType":0}],[0],0,[0],[0],[0]],[[{"name":"Bg_Black","rect":{"x":1758,"y":194,"width":2,"height":2},"offset":{"x":0,"y":0},"originalSize":{"width":2,"height":2},"rotated":false,"capInsets":[0,0,0,0],"packable":true,"pixelsToUnit":100,"pivot":{"x":0.5,"y":0.5},"meshType":0}],[0],0,[0],[0],[0]],[[{"name":"eft_str_m03","rect":{"x":1337,"y":1622,"width":99,"height":52},"offset":{"x":0,"y":-0.5},"originalSize":{"width":99,"height":57},"rotated":true,"capInsets":[0,0,0,0],"packable":true,"pixelsToUnit":100,"pivot":{"x":0.5,"y":0.5},"meshType":0}],[0],0,[0],[0],[0]],[[{"name":"FX_Brushing_01","rect":{"x":880,"y":1306,"width":168,"height":33},"offset":{"x":-6,"y":0.5},"originalSize":{"width":180,"height":40},"rotated":true,"capInsets":[0,0,0,0],"packable":true,"pixelsToUnit":100,"pivot":{"x":0.5,"y":0.5},"meshType":0}],[0],0,[0],[0],[0]],[[{"name":"deal_v2_c03","rect":{"x":124,"y":1209,"width":116,"height":151},"offset":{"x":0,"y":0},"originalSize":{"width":122,"height":155},"rotated":true,"capInsets":[0,0,0,0],"packable":true,"pixelsToUnit":100,"pivot":{"x":0.5,"y":0.5},"meshType":0}],[0],0,[0],[0],[0]],[[{"name":"deal_NW_nef_06","rect":{"x":1713,"y":653,"width":62,"height":108},"offset":{"x":0,"y":0},"originalSize":{"width":62,"height":108},"rotated":false,"capInsets":[0,0,0,0],"packable":true,"pixelsToUnit":100,"pivot":{"x":0.5,"y":0.5},"meshType":0}],[0],0,[0],[0],[0]],[[{"name":"PokSyb_sca_s5","rect":{"x":1634,"y":1167,"width":28,"height":124},"offset":{"x":0,"y":0},"originalSize":{"width":30,"height":126},"rotated":false,"capInsets":[0,0,0,0],"packable":true,"pixelsToUnit":100,"pivot":{"x":0.5,"y":0.5},"meshType":0}],[0],0,[0],[0],[0]],[[{"name":"board_button_q","rect":{"x":440,"y":992,"width":48,"height":48},"offset":{"x":0,"y":0},"originalSize":{"width":48,"height":48},"rotated":false,"capInsets":[0,0,0,0],"packable":true,"pixelsToUnit":100,"pivot":{"x":0.5,"y":0.5},"meshType":0}],[0],0,[0],[0],[0]],[[{"name":"PokSyb_sca_s3","rect":{"x":231,"y":1106,"width":96,"height":123},"offset":{"x":0,"y":-0.5},"originalSize":{"width":98,"height":126},"rotated":true,"capInsets":[0,0,0,0],"packable":true,"pixelsToUnit":100,"pivot":{"x":0.5,"y":0.5},"meshType":0}],[0],0,[0],[0],[0]],[[{"name":"FG_Multiplier_BG","rect":{"x":3,"y":590,"width":640,"height":70},"offset":{"x":0,"y":0},"originalSize":{"width":640,"height":70},"rotated":false,"capInsets":[0,0,0,0],"packable":true,"pixelsToUnit":100,"pivot":{"x":0.5,"y":0.5},"meshType":0}],[0],0,[0],[0],[0]],[[{"name":"FX_Light_04","rect":{"x":1490,"y":1343,"width":128,"height":128},"offset":{"x":0,"y":0},"originalSize":{"width":128,"height":128},"rotated":false,"capInsets":[0,0,0,0],"packable":true,"pixelsToUnit":100,"pivot":{"x":0.5,"y":0.5},"meshType":0}],[0],0,[0],[0],[0]],[[{"name":"Combo_bg","rect":{"x":1295,"y":326,"width":420,"height":90},"offset":{"x":0,"y":0},"originalSize":{"width":420,"height":90},"rotated":false,"capInsets":[0,0,0,0],"packable":true,"pixelsToUnit":100,"pivot":{"x":0.5,"y":0.5},"meshType":0}],[0],0,[0],[0],[0]],[[{"name":"deal_v2_c05","rect":{"x":1634,"y":1039,"width":122,"height":31},"offset":{"x":0,"y":0},"originalSize":{"width":124,"height":33},"rotated":true,"capInsets":[0,0,0,0],"packable":true,"pixelsToUnit":100,"pivot":{"x":0.5,"y":0.5},"meshType":0}],[0],0,[0],[0],[0]],[[{"name":"FG_BigWin_win","rect":{"x":1292,"y":838,"width":374,"height":195},"offset":{"x":6,"y":-56.5},"originalSize":{"width":580,"height":326},"rotated":false,"capInsets":[0,0,0,0],"packable":true,"pixelsToUnit":100,"pivot":{"x":0.5,"y":0.5},"meshType":0}],[0],0,[0],[0],[0]],[[{"name":"deal_NW_c01","rect":{"x":1713,"y":767,"width":58,"height":240},"offset":{"x":0,"y":0},"originalSize":{"width":60,"height":242},"rotated":false,"capInsets":[0,0,0,0],"packable":true,"pixelsToUnit":100,"pivot":{"x":0.5,"y":0.5},"meshType":0}],[0],0,[0],[0],[0]],[[{"name":"Light_11","rect":{"x":1295,"y":169,"width":422,"height":151},"offset":{"x":7,"y":-2},"originalSize":{"width":436,"height":155},"rotated":false,"capInsets":[0,0,0,0],"packable":true,"pixelsToUnit":100,"pivot":{"x":0.5,"y":0.5},"meshType":0}],[0],0,[0],[0],[0]],[[{"name":"Black_Matte","rect":{"x":780,"y":1308,"width":20,"height":20},"offset":{"x":0,"y":0},"originalSize":{"width":20,"height":20},"rotated":false,"capInsets":[0,0,0,0],"packable":true,"pixelsToUnit":100,"pivot":{"x":0.5,"y":0.5},"meshType":0}],[0],0,[0],[0],[0]],[[{"name":"eft_bol_02","rect":{"x":1337,"y":1727,"width":40,"height":40},"offset":{"x":0,"y":0},"originalSize":{"width":40,"height":40},"rotated":false,"capInsets":[0,0,0,0],"packable":true,"pixelsToUnit":100,"pivot":{"x":0.5,"y":0.5},"meshType":0}],[0],0,[0],[0],[0]],[[{"name":"Gold_02b","rect":{"x":1395,"y":1702,"width":73,"height":76},"offset":{"x":2,"y":-1.5},"originalSize":{"width":85,"height":85},"rotated":true,"capInsets":[0,0,0,0],"packable":true,"pixelsToUnit":100,"pivot":{"x":0.5,"y":0.5},"meshType":0}],[0],0,[0],[0],[0]],[[{"name":"FG_str_c02","rect":{"x":1295,"y":422,"width":410,"height":412},"offset":{"x":0,"y":0},"originalSize":{"width":410,"height":412},"rotated":true,"capInsets":[0,0,0,0],"packable":true,"pixelsToUnit":100,"pivot":{"x":0.5,"y":0.5},"meshType":0}],[0],0,[0],[0],[0]],[[{"name":"Light_02","rect":{"x":1624,"y":1468,"width":128,"height":128},"offset":{"x":0,"y":0},"originalSize":{"width":128,"height":128},"rotated":false,"capInsets":[0,0,0,0],"packable":true,"pixelsToUnit":100,"pivot":{"x":0.5,"y":0.5},"meshType":0}],[0],0,[0],[0],[0]],[[{"name":"BG_Top","rect":{"x":3,"y":666,"width":320,"height":534},"offset":{"x":0,"y":0},"originalSize":{"width":320,"height":534},"rotated":true,"capInsets":[0,0,0,0],"packable":true,"pixelsToUnit":100,"pivot":{"x":0.5,"y":0.5},"meshType":0}],[0],0,[0],[0],[0]],[[{"name":"Light_02","rect":{"x":1490,"y":1477,"width":128,"height":128},"offset":{"x":0,"y":0},"originalSize":{"width":128,"height":128},"rotated":false,"capInsets":[0,0,0,0],"packable":true,"pixelsToUnit":100,"pivot":{"x":0.5,"y":0.5},"meshType":0}],[0],0,[0],[0],[0]],[[{"name":"1f_star_6","rect":{"x":1713,"y":520,"width":127,"height":63},"offset":{"x":0.5,"y":1.5},"originalSize":{"width":128,"height":128},"rotated":true,"capInsets":[0,0,0,0],"packable":true,"pixelsToUnit":100,"pivot":{"x":0.5,"y":0.5},"meshType":0}],[0],0,[0],[0],[0]],[[{"name":"MulBoard_02","rect":{"x":993,"y":1445,"width":204,"height":68},"offset":{"x":0,"y":0},"originalSize":{"width":204,"height":68},"rotated":true,"capInsets":[0,0,0,0],"packable":true,"pixelsToUnit":100,"pivot":{"x":0.5,"y":0.5},"meshType":0}],[0],0,[0],[0],[0]],[[{"name":"4win","rect":{"x":1397,"y":1410,"width":100,"height":87},"offset":{"x":0,"y":0.5},"originalSize":{"width":100,"height":100},"rotated":true,"capInsets":[0,0,0,0],"packable":true,"pixelsToUnit":100,"pivot":{"x":0.5,"y":0.5},"meshType":0}],[0],0,[0],[0],[0]],[[{"name":"PokSyb_sca_s6","rect":{"x":648,"y":1124,"width":66,"height":124},"offset":{"x":0,"y":0},"originalSize":{"width":68,"height":126},"rotated":true,"capInsets":[0,0,0,0],"packable":true,"pixelsToUnit":100,"pivot":{"x":0.5,"y":0.5},"meshType":0}],[0],0,[0],[0],[0]],[[{"name":"Board_ways_bg","rect":{"x":880,"y":1480,"width":170,"height":24},"offset":{"x":0,"y":0},"originalSize":{"width":170,"height":24},"rotated":true,"capInsets":[0,0,0,0],"packable":true,"pixelsToUnit":100,"pivot":{"x":0.5,"y":0.5},"meshType":0}],[0],0,[0],[0],[0]],[[{"name":"eft_bg_01","rect":{"x":806,"y":1308,"width":20,"height":20},"offset":{"x":0,"y":0},"originalSize":{"width":20,"height":20},"rotated":false,"capInsets":[0,0,0,0],"packable":true,"pixelsToUnit":100,"pivot":{"x":0.5,"y":0.5},"meshType":0}],[0],0,[0],[0],[0]]]]
